tc_pysh/__init__.py
tc_pysh/__main__.py
tc_pysh/command.py
tc_pysh/file.py
tc_pysh/interactive.py
tc_pysh/interpreter.py
tc_pysh/path.py
tc_pysh/py.typed
tc_pysh/query.py
tc_pysh/script_utils.py
tc_pysh/stream.py
tc_pysh/utils.py
tc_pysh/zipper.py
tc_pysh/test/test_path.py
tc_pysh/test/test_stream.py
tc_pysh-0.9.0.dist-info/METADATA
tc_pysh-0.9.0.dist-info/WHEEL
tc_pysh-0.9.0.dist-info/entry_points.txt
tc_pysh-0.9.0.dist-info/licenses/LICENSE
tc_pysh-0.9.0.dist-info/RECORD
