Metadata-Version: 2.3
Name: tc-pysh
Version: 0.9.0
Summary: Some utils for file manipulation scripts
Project-URL: Homepage, https://git.sr.ht/~lattay/pysh
Author-email: Théo Cavignac <theo.cavignac+dev@gmail.com>
Classifier: Environment :: Console
Classifier: License :: OSI Approved :: BSD License
Classifier: Programming Language :: Python :: 3.7
Classifier: Topic :: Software Development :: User Interfaces
